fuzzy_httpserver/__init__.py
fuzzy_httpserver/server.py
fuzzy_httpserver-1.5.0.dist-info/METADATA
fuzzy_httpserver-1.5.0.dist-info/WHEEL
fuzzy_httpserver-1.5.0.dist-info/entry_points.txt
fuzzy_httpserver-1.5.0.dist-info/top_level.txt
fuzzy_httpserver-1.5.0.dist-info/RECORD
