Metadata-Version: 2.4
Name: fuzzy-httpserver
Version: 1.5.0
Summary: Fuzzy matching HTTP file server with autocomplete and fallback
Home-page: https://github.com/PakCyberbot/fuzzy-httpserver
Author: PakCyberbot
Author-email: pakcyberbot@pakcyberbot.com
Project-URL: Source, https://github.com/PakCyberbot/fuzzy-httpserver
Project-URL: Bug Tracker, https://github.com/PakCyberbot/fuzzy-httpserver/issues
Classifier: Programming Language :: Python :: 3
Requires-Python: >=3.6
Dynamic: author
Dynamic: author-email
Dynamic: classifier
Dynamic: description
Dynamic: description-content-type
Dynamic: home-page
Dynamic: project-url
Dynamic: requires-python
Dynamic: summary
